LICENSE
MANIFEST.in
README.md
setup.py
egl_probe/CMakeLists.txt
egl_probe/__init__.py
egl_probe/get_available_devices.py
egl_probe/query_devices.cpp
egl_probe/test_device.cpp
egl_probe/glad/egl.cpp
egl_probe/glad/gl.cpp
egl_probe/glad/glx_dyn.cpp
egl_probe/glad/linmath.h
egl_probe/glad/EGL/eglplatform.h
egl_probe/glad/KHR/khrplatform.h
egl_probe/glad/X11/X.h
egl_probe/glad/X11/XKBlib.h
egl_probe/glad/X11/Xatom.h
egl_probe/glad/X11/Xfuncproto.h
egl_probe/glad/X11/Xfuncs.h
egl_probe/glad/X11/Xlib.h
egl_probe/glad/X11/XlibConf.h
egl_probe/glad/X11/Xlibint.h
egl_probe/glad/X11/Xmd.h
egl_probe/glad/X11/Xosdefs.h
egl_probe/glad/X11/Xproto.h
egl_probe/glad/X11/Xprotostr.h
egl_probe/glad/X11/Xutil.h
egl_probe/glad/X11/cursorfont.h
egl_probe/glad/X11/keysym.h
egl_probe/glad/X11/keysymdef.h
egl_probe/glad/X11/extensions/XKB.h
egl_probe/glad/X11/extensions/XKBstr.h
egl_probe/glad/X11/extensions/XShm.h
egl_probe/glad/X11/extensions/Xext.h
egl_probe/glad/X11/extensions/extutil.h
egl_probe/glad/X11/extensions/shape.h
egl_probe/glad/X11/extensions/shapeconst.h
egl_probe/glad/X11/extensions/shm.h
egl_probe/glad/glad/egl.h
egl_probe/glad/glad/gl.h
egl_probe/glad/glad/glx.h
hf_egl_probe.egg-info/PKG-INFO
hf_egl_probe.egg-info/SOURCES.txt
hf_egl_probe.egg-info/dependency_links.txt
hf_egl_probe.egg-info/not-zip-safe
hf_egl_probe.egg-info/top_level.txt