Metadata-Version: 2.4
Name: hf_egl_probe
Version: 1.0.2
Home-page: https://github.com/huggingface/egl_probe
Author: Stanford University
License-File: LICENSE
Dynamic: author
Dynamic: description
Dynamic: description-content-type
Dynamic: home-page
Dynamic: license-file
